counter_tb/counter.v
module counter #(
    // Parameters
    parameter COUNTER_SIZE = 8,
    parameter START_VALUE = 8'b00000000,
    parameter STOP_VALUE = 8'b11111111,
    parameter STEP_VALUE = 1'b1
) (
    // Inputs
    input clock,
    input reset,
    input start,
    
    // Outputs
    output reg done,
    output reg enabled,
    output reg [COUNTER_SIZE-1:0] value
);

    // States
    localparam STATE_WAIT = 1'b0;
    localparam STATE_COUNT = 1'b1;
    localparam OFF = 1'b0;
    localparam ON = 1'b1;

    // Internal Storage
    reg state;

    always @ (posedge clock or posedge reset) begin
        if (reset) begin
            state <= STATE_WAIT;
            enabled <= OFF;
            done <= OFF;
        end else begin
            case (state)
                STATE_WAIT: begin
                    if (start) begin
                        state <= STATE_COUNT;
                        value <= START_VALUE;
                        enabled <= ON;
                    end else begin
                        done <= OFF;
                        enabled <= OFF;
                    end
                end
                STATE_COUNT: begin
                    // Prep done line
                    if (value == STOP_VALUE - STEP_VALUE) begin
                        value <= value + STEP_VALUE;
                        enabled <= ON;
                        done <= ON;
                    // Transition to Wait State
                    end else if (value == STOP_VALUE) begin
                        enabled <= OFF;
                        done <= ON;
                        state <= STATE_WAIT;
                    // or Cycle the Counter
                    end else begin
                        value <= value + STEP_VALUE;
                        enabled <= ON;
                    end
                end
            endcase
        end
    end
endmodule

counter_tb/counter_tb.v
`timescale 1 ns / 1 ns

module counter_tb ();
    localparam DURATION = 10000;
    localparam LED_COUNT = 4;

    reg reset = 0;
    reg start = 0;
    reg clock = 0;
    wire [LED_COUNT - 1:0] led;

    wire done_up;
    wire done_dn;
    wire enabled_up;
    wire enabled_dn;
    wire [LED_COUNT - 1:0] value_up;
    wire [LED_COUNT - 1:0] value_dn;
    // Startup Logic
    wire start_up = start & ~(enabled_up | enabled_dn | reset);
    // Transition Logic
    wire start_dn = done_up;
    // LED Driver Logic
    assign led = ({LED_COUNT{enabled_up}}&value_up)|({LED_COUNT{enabled_dn}}&value_dn);

    // Instantiate the clock
    always begin
        #41
        clock = ~clock;
    end

    initial begin
        #10
        reset = 1'b1;
        #10
        reset = 1'b0;
        #10
        start = 1'b1;
        #20
        start = 1'b0;
    end

    initial begin
        $dumpfile("counter_tb.vcd");
        $dumpvars(0, counter_tb);
        #(DURATION)
        $display("Finished!");
        $finish;
    end


    // clock_divider #(
    //     .CLOCK_INTERVAL(5)
    // ) clock1 (
    //     .clock_in(clock_in),
    //     .reset(reset),
    //     .clock_out(clock)
    // );

    // Instantiate the Up Counter
    counter #(
        .COUNTER_SIZE(4),
        .START_VALUE(4'd1),
        .STOP_VALUE(4'b1111),
        .STEP_VALUE(4'd1)
    ) counter_up (
        .clock(clock),
        .reset(reset),
        .start(start_up),
        .done(done_up),
        .enabled(enabled_up),
        .value(value_up)
    );

    // Instantiate the Down Counter
    counter #(
        .COUNTER_SIZE(4),
        .START_VALUE(4'b1110),
        .STOP_VALUE(4'b0000),
        .STEP_VALUE(4'b1111)
    ) counter_dn (
        .clock(clock),
        .reset(reset),
        .start(start_dn),
        .done(done_dn),
        .enabled(enabled_dn),
        .value(value_dn)
    );

endmodule

counter_tb/counter_tb.vcd
$date
	Sun Feb 05 10:20:11 2023
$end
$version
	Icarus Verilog
$end
$timescale
	1ps
$end
$scope module counter_tb $end
$var wire 4 ! led [3:0] $end
$var wire 1 " start_dn $end
$var wire 1 # start_up $end
$var wire 4 $ value_up [3:0] $end
$var wire 4 % value_dn [3:0] $end
$var wire 1 & enabled_up $end
$var wire 1 ' enabled_dn $end
$var wire 1 ( done_up $end
$var wire 1 ) done_dn $end
$var reg 1 * clock $end
$var reg 1 + reset $end
$var reg 1 , start $end
$scope module counter_dn $end
$var wire 1 * clock $end
$var wire 1 + reset $end
$var wire 1 " start $end
$var reg 1 ) done $end
$var reg 1 ' enabled $end
$var reg 1 - state $end
$var reg 4 . value [3:0] $end
$upscope $end
$scope module counter_up $end
$var wire 1 * clock $end
$var wire 1 + reset $end
$var wire 1 # start $end
$var reg 1 ( done $end
$var reg 1 & enabled $end
$var reg 1 / state $end
$var reg 4 0 value [3:0] $end
$upscope $end
$upscope $end
$enddefinitions $end
#0
$dumpvars
bx 0
x/
bx .
x-
0,
0+
0*
x)
x(
x'
x&
bx %
bx $
0#
x"
bx !
$end
#10000
b0 !
0"
0(
0&
0/
0)
0'
0-
1+
#20000
0+
#30000
1#
1,
#41000
0#
b1 !
1&
b1 $
b1 0
1/
1*
#50000
0,
#82000
0*
#123000
b10 !
b10 $
b10 0
1*
#164000
0*
#205000
b11 !
b11 $
b11 0
1*
#246000
0*
#287000
b100 !
b100 $
b100 0
1*
#328000
0*
#369000
b101 !
b101 $
b101 0
1*
#410000
0*
#451000
b110 !
b110 $
b110 0
1*
#492000
0*
#533000
b111 !
b111 $
b111 0
1*
#574000
0*
#615000
b1000 !
b1000 $
b1000 0
1*
#656000
0*
#697000
b1001 !
b1001 $
b1001 0
1*
#738000
0*
#779000
b1010 !
b1010 $
b1010 0
1*
#820000
0*
#861000
b1011 !
b1011 $
b1011 0
1*
#902000
0*
#943000
b1100 !
b1100 $
b1100 0
1*
#984000
0*
#1025000
b1101 !
b1101 $
b1101 0
1*
#1066000
0*
#1107000
b1110 !
b1110 $
b1110 0
1*
#1148000
0*
#1189000
b1111 !
1"
1(
b1111 $
b1111 0
1*
#1230000
0*
#1271000
b1110 !
0/
0&
1'
b1110 %
b1110 .
1-
1*
#1312000
0*
#1353000
b1101 !
b1101 %
b1101 .
0"
0(
1*
#1394000
0*
#1435000
b1100 !
b1100 %
b1100 .
1*
#1476000
0*
#1517000
b1011 !
b1011 %
b1011 .
1*
#1558000
0*
#1599000
b1010 !
b1010 %
b1010 .
1*
#1640000
0*
#1681000
b1001 !
b1001 %
b1001 .
1*
#1722000
0*
#1763000
b1000 !
b1000 %
b1000 .
1*
#1804000
0*
#1845000
b111 !
b111 %
b111 .
1*
#1886000
0*
#1927000
b110 !
b110 %
b110 .
1*
#1968000
0*
#2009000
b101 !
b101 %
b101 .
1*
#2050000
0*
#2091000
b100 !
b100 %
b100 .
1*
#2132000
0*
#2173000
b11 !
b11 %
b11 .
1*
#2214000
0*
#2255000
b10 !
b10 %
b10 .
1*
#2296000
0*
#2337000
b1 !
b1 %
b1 .
1*
#2378000
0*
#2419000
b0 !
1)
b0 %
b0 .
1*
#2460000
0*
#2501000
0-
0'
1*
#2542000
0*
#2583000
0)
1*
