debounceer_tb/debouncer.v
//------------------------------------------------------------------
//-- Debounce Module
//------------------------------------------------------------------

//-- Template for the top entity
module debouncer #(
    // Parameters
    parameter CLOCK_SIZE = 24,
    parameter CLOCK_LENGTH = 12000,
    parameter CLOCK_START = 24'd0,
    parameter CLOCK_LIMIT = 24'd5999
) (
    // Inputs
    input   reset,
    input   button_in,
    input   clock_in,
    // Outputs
    output  reg button_out
);

    // States
    localparam OFF   = 1'b0;
    localparam ON   = 1'b1;

    // Internal Storage
    reg [(CLOCK_SIZE - 1):00] clock_counter;
    reg state;
    reg debounce_clk;

    // Debounce Clock
    always @ (posedge clock_in or posedge reset) begin
        if (reset) begin
            clock_counter <= CLOCK_START;
            debounce_clk <= 0;
        end else if (clock_counter == CLOCK_LIMIT) begin
            clock_counter <= CLOCK_START;
            debounce_clk <= ~debounce_clk;
        end else begin
            clock_counter <= clock_counter + 1'b1;
        end
    end

    // Debounce FSM
    always @ (posedge debounce_clk or posedge reset) begin
        //Reset to Idle
        if (reset) begin
            state <= OFF;
            button_out <= OFF;
        end else begin
            case (state)
                OFF: begin
                    //Transition to Debounce
                    if (button_in==ON) begin
                        state <= ON;
                        button_out <= ON;
                    end
                end

                ON: begin
                    //Transition to Idle
                    if (button_in==OFF) begin
                        state <= OFF;
                        button_out <= OFF;
                    end
                end
            endcase
        end
    end
endmodule

debouncer_tb/debouncer_tb.v
`timescale 1 ns / 1 ns

module debouncer_tb ();
    localparam DURATION = 1000000;
    reg reset = 0;
    reg button_in = 0;
    reg clock = 0;
    reg [4] i;
    wire button;

    // Instantiate the clock
    always begin
        #41
        clock = ~clock;
    end

    initial begin
        #10
        reset = 1'b1;
        #10
        reset = 1'b0;
    end

    always begin
        // Random period where the button is off
        #($urandom_range(18000,6000));
        // Bounce Loop
        // Random sequence of button Bounce
        for (i = $urandom_range(5,9);i>0;i--) begin
            // Button Bounce
            button_in = 1;
            #($urandom_range(130,50));
            button_in = 0;
            #($urandom_range(130,50));
        end
        button_in = 1;
        #($urandom_range(13000,5000));
        button_in = 0;

    end

    initial begin
        $dumpfile("debouncer_tb.vcd");
        $dumpvars(0, debouncer_tb);
        #(DURATION)
        $display("Finished!");
        $finish;
    end

    debouncer #(
        // Parameters
        .CLOCK_SIZE(24),
        .CLOCK_LENGTH(120),
        .CLOCK_START(24'd0),
        .CLOCK_LIMIT(24'd59)
    ) debouncer_sut (
        .reset(reset),
        .button_in(button_in),
        .clock_in(clock),
        .button_out(button)
    );
endmodule

debounceer_tb/debouncer_tb.vcd
$date
	Thu Feb 09 07:59:37 2023
$end
$version
	Icarus Verilog
$end
$timescale
	1ps
$end
$scope module debouncer_tb $end
$var wire 1 ! button $end
$var reg 1 " button_in $end
$var reg 1 # clock $end
$var reg 4 $ i [3:0] $end
$var reg 1 % reset $end
$scope module debouncer_sut $end
$var wire 1 " button_in $end
$var wire 1 # clock_in $end
$var wire 1 % reset $end
$var reg 1 ! button_out $end
$var reg 24 & clock_counter [23:0] $end
$var reg 1 ' debounce_clk $end
$var reg 1 ( state $end
$upscope $end
$upscope $end
$enddefinitions $end
#0
$dumpvars
x(
x'
bx &
0%
bx $
0#
0"
x!
$end
#10000
0!
0(
0'
b0 &
1%
#20000
0%
#41000
b1 &
1#
#82000
0#
#123000
b10 &
1#
#164000
0#
#205000
b11 &
1#
#246000
0#
#287000
b100 &
1#
#328000
0#
#369000
b101 &
1#
#410000
0#
#451000
b110 &
1#
#492000
0#
#533000
b111 &
1#
#574000
0#
#615000
b1000 &
1#
#656000
0#
#697000
b1001 &
1#
#738000
0#
#779000
b1010 &
1#
#820000
0#
#861000
b1011 &
1#
#902000
0#
#943000
b1100 &
1#
#984000
0#
#1025000
b1101 &
1#
#1066000
0#
#1107000
b1110 &
1#
#1148000
0#
#1189000
b1111 &
1#
#1230000
0#
#1271000
b10000 &
1#
#1312000
0#
#1353000
b10001 &
1#
#1394000
0#
#1435000
b10010 &
1#
#1476000
0#
#1517000
b10011 &
1#
#1558000
0#
#1599000
b10100 &
1#
#1640000
0#
#1681000
b10101 &
1#
#1722000
0#
#1763000
b10110 &
1#
#1804000
0#
#1845000
b10111 &
1#
#1886000
0#
#1927000
b11000 &
1#
#1968000
0#
#2009000
b11001 &
1#
#2050000
0#
#2091000
b11010 &
1#
#2132000
0#
#2173000
b11011 &
1#
#2214000
0#
#2255000
b11100 &
1#
#2296000
0#
#2337000
b11101 &
1#
#2378000
0#
#2419000
b11110 &
1#
#2460000
0#
#2501000
b11111 &
1#
#2542000
0#
#2583000
b100000 &
1#
#2624000
0#
#2665000
b100001 &
1#
#2706000
0#
#2747000
b100010 &
1#
#2788000
0#
#2829000
b100011 &
1#
#2870000
0#
#2911000
b100100 &
1#
#2952000
0#
#2993000
b100101 &
1#
#3034000
0#
#3075000
b100110 &
1#
#3116000
0#
#3157000
b100111 &
1#
#3198000
0#
#3239000
b101000 &
1#
#3280000
0#
#3321000
b101001 &
1#
#3362000
0#
#3403000
b101010 &
1#
#3444000
0#
#3485000
b101011 &
1#
#3526000
0#
#3567000
b101100 &
1#
#3608000
0#
#3649000
b101101 &
1#
#3690000
0#
#3731000
b101110 &
1#
#3772000
0#
#3813000
b101111 &
1#
#3854000
0#
#3895000
b110000 &
1#
#3936000
0#
#3977000
b110001 &
1#
#4018000
0#
#4059000
b110010 &
1#
#4100000
0#
#4141000
b110011 &
1#
#4182000
0#
#4223000
b110100 &
1#
#4264000
0#
#4305000
b110101 &
1#
#4346000
0#
#4387000
b110110 &
1#
#4428000
0#
#4469000
b110111 &
1#
#4510000
0#
#4551000
b111000 &
1#
#4592000
0#
#4633000
b111001 &
1#
#4674000
0#
#4715000
b111010 &
1#
#4756000
0#
#4797000
b111011 &
1#
#4838000
0#
#4879000
1'
b0 &
1#
#4920000
0#
#4961000
b1 &
1#
#5002000
0#
#5043000
b10 &
1#
#5084000
0#
#5125000
b11 &
1#
#5166000
0#
#5207000
b100 &
1#
#5248000
0#
#5289000
b101 &
1#
#5330000
0#
#5371000
b110 &
1#
#5412000
0#
#5453000
b111 &
1#
#5494000
0#
#5535000
b1000 &
1#
#5576000
0#
#5617000
b1001 &
1#
#5658000
0#
#5699000
b1010 &
1#
#5740000
0#
#5781000
b1011 &
1#
#5822000
0#
#5863000
b1100 &
1#
#5904000
0#
#5945000
b1101 &
1#
#5986000
0#
#6027000
b1110 &
1#
#6068000
0#
#6109000
b1111 &
1#
#6150000
0#
#6191000
b10000 &
1#
#6232000
0#
#6273000
b10001 &
1#
#6314000
0#
#6355000
b10010 &
1#
#6396000
0#
#6437000
b10011 &
1#
#6478000
0#
#6519000
b10100 &
1#
#6560000
0#
#6601000
b10101 &
1#
#6642000
0#
#6683000
b10110 &
1#
#6724000
0#
#6765000
b10111 &
1#
#6806000
0#
#6847000
b11000 &
1#
#6888000
0#
#6929000
b11001 &
1#
#6970000
0#
#7011000
b11010 &
1#
#7052000
0#
#7093000
b11011 &
1#
#7134000
0#
#7175000
b11100 &
1#
#7216000
0#
#7257000
b11101 &
1#
#7298000
0#
#7339000
b11110 &
1#
#7380000
0#
#7421000
b11111 &
1#
#7462000
0#
#7503000
b100000 &
1#
#7544000
0#
#7585000
b100001 &
1#
#7626000
0#
#7667000
b100010 &
1#
#7708000
0#
#7749000
b100011 &
1#
#7790000
0#
#7831000
b100100 &
1#
#7872000
0#
#7913000
b100101 &
1#
#7954000
0#
#7995000
b100110 &
1#
#8036000
0#
#8077000
b100111 &
1#
#8118000
0#
#8159000
b101000 &
1#
#8200000
0#
#8241000
b101001 &
1#
#8282000
0#
#8323000
b101010 &
1#
#8364000
0#
#8405000
b101011 &
1#
#8446000
0#
#8487000
b101100 &
1#
#8528000
0#
#8569000
b101101 &
1#
#8610000
0#
#8651000
b101110 &
1#
#8692000
0#
#8733000
b101111 &
1#
#8774000
0#
#8815000
b110000 &
1#
#8856000
0#
#8897000
b110001 &
1#
#8938000
0#
#8979000
b110010 &
1#
#9020000
0#
#9061000
b110011 &
1#
#9102000
0#
#9143000
b110100 &
1#
#9184000
0#
#9225000
b110101 &
1#
#9266000
0#
#9307000
b110110 &
1#
#9348000
0#
#9389000
b110111 &
1#
#9430000
0#
#9471000
b111000 &
1#
#9512000
0#
#9553000
b111001 &
1#
#9594000
0#
#9635000
b111010 &
1#
#9676000
0#
#9717000
b111011 &
1#
#9758000
0#
#9799000
0'
b0 &
1#
#9840000
0#
#9881000
b1 &
1#
#9922000
0#
#9963000
b10 &
1#
#10004000
0#
#10045000
b11 &
1#
#10086000
0#
#10127000
b100 &
1#
#10168000
0#
#10209000
b101 &
1#
#10250000
0#
#10291000
b110 &
1#
#10332000
0#
#10373000
b111 &
1#
#10414000
0#
#10455000
b1000 &
1#
#10496000
0#
#10537000
b1001 &
1#
#10578000
0#
#10619000
b1010 &
1#
#10660000
0#
#10701000
b1011 &
1#
#10742000
0#
#10783000
b1100 &
1#
#10824000
0#
#10865000
b1101 &
1#
#10906000
0#
#10947000
b1110 &
1#
#10988000
0#
#11029000
b1111 &
1#
#11070000
0#
#11111000
b10000 &
1#
#11152000
0#
#11193000
b10001 &
1#
#11234000
0#
#11275000
b10010 &
1#
#11316000
0#
#11357000
b10011 &
1#
#11398000
0#
#11439000
b10100 &
1#
#11480000
0#
#11521000
b10101 &
1#
#11562000
0#
#11603000
b10110 &
1#
#11644000
0#
#11685000
b10111 &
1#
#11726000
0#
#11767000
b11000 &
1#
#11808000
0#
#11849000
b11001 &
1#
#11890000
0#
#11931000
b11010 &
1#
#11972000
0#
#12013000
b11011 &
1#
#12054000
0#
#12095000
b11100 &
1#
#12136000
0#
#12177000
b11101 &
1#
#12218000
0#
#12259000
b11110 &
1#
#12300000
0#
#12341000
b11111 &
1#
#12382000
0#
#12423000
b100000 &
1#
#12464000
0#
#12505000
b100001 &
1#
#12546000
0#
#12587000
b100010 &
1#
#12628000
0#
#12669000
b100011 &
1#
#12710000
0#
#12751000
b100100 &
1#
#12792000
0#
#12833000
b100101 &
1#
#12848000
1"
b110 $
#12874000
0#
#12899000
0"
#12915000
b100110 &
1#
#12956000
0#
#12964000
1"
b101 $
#12997000
b100111 &
1#
#13038000
0#
#13056000
0"
#13079000
b101000 &
1#
#13120000
0#
#13161000
b101001 &
1#
#13168000
1"
b100 $
#13202000
0#
#13234000
0"
#13243000
b101010 &
1#
#13284000
0#
#13286000
1"
b11 $
#13325000
b101011 &
1#
#13366000
0#
#13376000
0"
#13407000
b101100 &
1#
#13448000
0#
#13468000
1"
b10 $
#13489000
b101101 &
1#
#13530000
0#
#13571000
b101110 &
1#
#13577000
0"
#13612000
0#
#13653000
b101111 &
1#
#13677000
1"
b1 $
#13694000
0#
#13735000
b110000 &
1#
#13776000
0#
#13805000
0"
#13817000
b110001 &
1#
#13858000
0#
#13899000
b110010 &
1#
#13917000
1"
b0 $
#13940000
0#
#13981000
b110011 &
1#
#14022000
0#
#14063000
b110100 &
1#
#14104000
0#
#14145000
b110101 &
1#
#14186000
0#
#14227000
b110110 &
1#
#14268000
0#
#14309000
b110111 &
1#
#14350000
0#
#14391000
b111000 &
1#
#14432000
0#
#14473000
b111001 &
1#
#14514000
0#
#14555000
b111010 &
1#
#14596000
0#
#14637000
b111011 &
1#
#14678000
0#
#14719000
1!
1(
1'
b0 &
1#
#14760000
0#
#14801000
b1 &
1#
#14842000
0#
#14883000
b10 &
1#
#14924000
0#
#14965000
b11 &
1#
#15006000
0#
#15047000
b100 &
1#
#15088000
0#
#15129000
b101 &
1#
#15170000
0#
#15211000
b110 &
1#
#15252000
0#
#15293000
b111 &
1#
#15334000
0#
#15375000
b1000 &
1#
#15416000
0#
#15457000
b1001 &
1#
#15498000
0#
#15539000
b1010 &
1#
#15580000
0#
#15621000
b1011 &
1#
#15662000
0#
#15703000
b1100 &
1#
#15744000
0#
#15785000
b1101 &
1#
#15826000
0#
#15867000
b1110 &
1#
#15908000
0#
#15949000
b1111 &
1#
#15990000
0#
#16031000
b10000 &
1#
#16072000
0#
#16113000
b10001 &
1#
#16154000
0#
#16195000
b10010 &
1#
#16236000
0#
#16277000
b10011 &
1#
#16318000
0#
#16359000
b10100 &
1#
#16400000
0#
#16441000
b10101 &
1#
#16482000
0#
#16523000
b10110 &
1#
#16564000
0#
#16605000
b10111 &
1#
#16646000
0#
#16687000
b11000 &
1#
#16728000
0#
#16769000
b11001 &
1#
#16810000
0#
#16851000
b11010 &
1#
#16892000
0#
#16933000
b11011 &
1#
#16974000
0#
#17015000
b11100 &
1#
#17056000
0#
#17097000
b11101 &
1#
#17138000
0#
#17179000
b11110 &
1#
#17220000
0#
#17261000
b11111 &
1#
#17302000
0#
#17343000
b100000 &
1#
#17384000
0#
#17425000
b100001 &
1#
#17466000
0#
#17507000
b100010 &
1#
#17548000
0#
#17589000
b100011 &
1#
#17630000
0#
#17671000
b100100 &
1#
#17712000
0#
#17753000
b100101 &
1#
#17794000
0#
#17835000
b100110 &
1#
#17876000
0#
#17917000
b100111 &
1#
#17958000
0#
#17999000
b101000 &
1#
#18040000
0#
#18081000
b101001 &
1#
#18122000
0#
#18163000
b101010 &
1#
#18204000
0#
#18245000
b101011 &
1#
#18286000
0#
#18327000
b101100 &
1#
#18368000
0#
#18409000
b101101 &
1#
#18450000
0#
#18491000
b101110 &
1#
#18532000
0#
#18573000
b101111 &
1#
#18614000
0#
#18655000
b110000 &
1#
#18696000
0#
#18737000
b110001 &
1#
#18778000
0#
#18819000
b110010 &
1#
#18860000
0#
#18901000
b110011 &
1#
#18942000
0#
#18983000
b110100 &
1#
#19024000
0#
#19065000
b110101 &
1#
#19106000
0#
#19147000
b110110 &
1#
#19188000
0#
#19229000
b110111 &
1#
#19270000
0#
#19311000
b111000 &
1#
#19352000
0#
#19393000
b111001 &
1#
#19434000
0#
#19475000
b111010 &
1#
#19516000
0#
#19557000
b111011 &
1#
#19598000
0#
#19639000
0'
b0 &
1#
#19680000
0#
#19721000
b1 &
1#
#19762000
0#
#19803000
b10 &
1#
#19844000
0#
#19885000
b11 &
1#
#19926000
0#
#19967000
b100 &
1#
#20008000
0#
#20049000
b101 &
1#
#20090000
0#
#20131000
b110 &
1#
#20172000
0#
#20213000
b111 &
1#
#20254000
0#
#20295000
b1000 &
1#
#20336000
0#
#20377000
b1001 &
1#
#20418000
0#
#20459000
b1010 &
1#
#20500000
0#
#20541000
b1011 &
1#
#20582000
0#
#20623000
b1100 &
1#
#20664000
0#
#20705000
b1101 &
1#
#20746000
0#
#20787000
b1110 &
1#
#20828000
0#
#20869000
b1111 &
1#
#20910000
0#
#20951000
b10000 &
1#
#20992000
0#
#21033000
b10001 &
1#
#21074000
0#
#21115000
b10010 &
1#
#21156000
0#
#21197000
b10011 &
1#
#21238000
0#
#21279000
b10100 &
1#
#21320000
0#
#21361000
b10101 &
1#
#21402000
0#
#21443000
b10110 &
1#
#21484000
0#
#21525000
b10111 &
1#
#21566000
0#
#21607000
b11000 &
1#
#21648000
0#
#21689000
b11001 &
1#
#21730000
0#
#21771000
b11010 &
1#
#21812000
0#
#21853000
b11011 &
1#
#21894000
0#
#21935000
b11100 &
1#
#21976000
0#
#22017000
b11101 &
1#
#22058000
0#
#22099000
b11110 &
1#
#22140000
0#
#22181000
b11111 &
1#
#22222000
0#
#22263000
b100000 &
1#
#22304000
0#
#22345000
b100001 &
1#
#22386000
0#
#22427000
b100010 &
1#
#22468000
0#
#22509000
b100011 &
1#
#22550000
0#
#22591000
b100100 &
1#
#22632000
0#
#22673000
b100101 &
1#
#22714000
0#
#22755000
b100110 &
1#
#22796000
0#
#22837000
b100111 &
1#
#22878000
0#
#22919000
b101000 &
1#
#22960000
0#
#23001000
b101001 &
1#
#23042000
0#
#23083000
b101010 &
1#
#23124000
0#
#23165000
b101011 &
1#
#23206000
0#
#23247000
b101100 &
1#
#23288000
0#
#23329000
b101101 &
1#
#23370000
0#
#23411000
b101110 &
1#
#23452000
0#
#23493000
b101111 &
1#
#23534000
0#
#23575000
b110000 &
1#
#23616000
0#
#23657000
b110001 &
1#
#23698000
0#
#23739000
b110010 &
1#
#23780000
0#
#23821000
b110011 &
1#
#23862000
0#
#23903000
b110100 &
1#
#23944000
0#
#23985000
b110101 &
1#
#24026000
0#
#24067000
b110110 &
1#
#24108000
0#
#24149000
b110111 &
1#
#24190000
0#
#24231000
b111000 &
1#
#24272000
0#
#24313000
b111001 &
1#
#24354000
0#
#24395000
b111010 &
1#
#24436000
0#
#24477000
b111011 &
1#
#24518000
0#
#24559000
1'
b0 &
1#
#24600000
0#
#24641000
b1 &
1#
#24682000
0#
#24723000
b10 &
1#
#24764000
0#
#24805000
b11 &
1#
#24846000
0#
#24887000
b100 &
1#
#24928000
0#
#24969000
b101 &
1#
#25010000
0#
#25051000
b110 &
1#
#25092000
0#
#25133000
b111 &
1#
#25174000
0#
#25215000
b1000 &
1#
#25256000
0#
#25297000
b1001 &
1#
#25338000
0#
#25379000
b1010 &
1#
#25420000
0#
#25461000
b1011 &
1#
#25502000
0#
#25543000
b1100 &
1#
#25584000
0#
#25625000
b1101 &
1#
#25666000
0#
#25707000
b1110 &
1#
#25748000
0#
#25789000
b1111 &
1#
#25830000
0#
#25871000
b10000 &
1#
#25912000
0#
#25953000
b10001 &
1#
#25994000
0#
#26035000
b10010 &
1#
#26076000
0#
#26117000
b10011 &
1#
#26158000
0#
#26199000
b10100 &
1#
#26240000
0#
#26281000
b10101 &
1#
#26322000
0#
#26363000
b10110 &
1#
#26404000
0#
#26445000
b10111 &
1#
#26486000
0#
#26527000
b11000 &
1#
#26568000
0#
#26609000
b11001 &
1#
#26650000
0#
#26691000
b11010 &
1#
#26732000
0#
#26773000
b11011 &
1#
#26814000
0#
#26823000
0"
#26855000
b11100 &
1#
#26896000
0#
#26937000
b11101 &
1#
#26978000
0#
#27019000
b11110 &
1#
#27060000
0#
#27101000
b11111 &
1#
#27142000
0#
#27183000
b100000 &
1#
#27224000
0#
#27265000
b100001 &
1#
#27306000
0#
#27347000
b100010 &
1#
#27388000
0#
#27429000
b100011 &
1#
#27470000
0#
#27511000
b100100 &
1#
#27552000
0#
#27593000
b100101 &
1#
#27634000
0#
#27675000
b100110 &
1#
#27716000
0#
#27757000
b100111 &
1#
#27798000
0#
#27839000
b101000 &
1#
#27880000
0#
#27921000
b101001 &
1#
#27962000
0#
#28003000
b101010 &
1#
#28044000
0#
#28085000
b101011 &
1#
#28126000
0#
#28167000
b101100 &
1#
#28208000
0#
#28249000
b101101 &
1#
#28290000
0#
#28331000
b101110 &
1#
#28372000
0#
#28413000
b101111 &
1#
#28454000
0#
#28495000
b110000 &
1#
#28536000
0#
#28577000
b110001 &
1#
#28618000
0#
#28659000
b110010 &
1#
#28700000
0#
#28741000
b110011 &
1#
#28782000
0#
#28823000
b110100 &
1#
#28864000
0#
#28905000
b110101 &
1#
#28946000
0#
#28987000
b110110 &
1#
#29028000
0#
#29069000
b110111 &
1#
#29110000
0#
#29151000
b111000 &
1#
#29192000
0#
#29233000
b111001 &
1#
#29274000
0#
#29315000
b111010 &
1#
#29356000
0#
#29397000
b111011 &
1#
#29438000
0#
#29479000
0'
b0 &
1#
#29520000
0#
#29561000
b1 &
1#
#29602000
0#
#29643000
b10 &
1#
#29684000
0#
#29725000
b11 &
1#
#29766000
0#
#29807000
b100 &
1#
#29848000
0#
#29889000
b101 &
1#
#29930000
0#
#29971000
b110 &
1#
#30012000
0#
#30053000
b111 &
1#
#30094000
0#
#30135000
b1000 &
1#
#30176000
0#
#30217000
b1001 &
1#
#30258000
0#
#30299000
b1010 &
1#
#30340000
0#
#30381000
b1011 &
1#
#30422000
0#
#30463000
b1100 &
1#
#30504000
0#
#30545000
b1101 &
1#
#30586000
0#
#30627000
b1110 &
1#
#30668000
0#
#30709000
b1111 &
1#
#30750000
0#
#30791000
b10000 &
1#
#30832000
0#
#30873000
b10001 &
1#
#30914000
0#
#30955000
b10010 &
1#
#30996000
0#
#31037000
b10011 &
1#
#31078000
0#
#31119000
b10100 &
1#
#31160000
0#
#31201000
b10101 &
1#
#31242000
0#
#31283000
b10110 &
1#
#31324000
0#
#31365000
b10111 &
1#
#31406000
0#
#31447000
b11000 &
1#
#31488000
0#
#31529000
b11001 &
1#
#31570000
0#
#31611000
b11010 &
1#
#31652000
0#
#31693000
b11011 &
1#
#31734000
0#
#31775000
b11100 &
1#
#31816000
0#
#31857000
b11101 &
1#
#31898000
0#
#31939000
b11110 &
1#
#31980000
0#
#32021000
b11111 &
1#
#32062000
0#
#32103000
b100000 &
1#
#32144000
0#
#32185000
b100001 &
1#
#32226000
0#
#32267000
b100010 &
1#
#32308000
0#
#32349000
b100011 &
1#
#32390000
0#
#32431000
b100100 &
1#
#32472000
0#
#32513000
b100101 &
1#
#32554000
0#
#32595000
b100110 &
1#
#32636000
0#
#32677000
b100111 &
1#
#32718000
0#
#32759000
b101000 &
1#
#32800000
0#
#32841000
b101001 &
1#
#32882000
0#
#32923000
b101010 &
1#
#32964000
0#
#33005000
b101011 &
1#
#33046000
0#
#33087000
b101100 &
1#
#33128000
0#
#33169000
b101101 &
1#
#33210000
0#
#33251000
b101110 &
1#
#33292000
0#
#33333000
b101111 &
1#
#33374000
0#
#33415000
b110000 &
1#
#33456000
0#
#33497000
b110001 &
1#
#33538000
0#
#33579000
b110010 &
1#
#33620000
0#
#33661000
b110011 &
1#
#33702000
0#
#33743000
b110100 &
1#
#33784000
0#
#33825000
b110101 &
1#
#33866000
0#
#33907000
b110110 &
1#
#33948000
0#
#33989000
b110111 &
1#
#34030000
0#
#34071000
b111000 &
1#
#34112000
0#
#34153000
b111001 &
1#
#34194000
0#
#34235000
b111010 &
1#
#34276000
0#
#34317000
b111011 &
1#
#34358000
0#
#34399000
0!
0(
1'
b0 &
1#
#34440000
0#
#34481000
b1 &
1#
#34522000
0#
#34563000
b10 &
1#
#34604000
0#
#34645000
b11 &
1#
#34686000
0#
#34727000
b100 &
1#
#34768000
0#
#34809000
b101 &
1#
#34850000
0#
#34891000
b110 &
1#
#34932000
0#
#34973000
b111 &
1#
#35014000
0#
#35055000
b1000 &
1#
#35096000
0#
#35137000
b1001 &
1#
#35178000
0#
#35219000
b1010 &
1#
#35260000
0#
#35301000
b1011 &
1#
#35342000
0#
#35383000
b1100 &
1#
#35424000
0#
#35465000
b1101 &
1#
#35506000
0#
#35547000
b1110 &
1#
#35588000
0#
#35629000
b1111 &
1#
#35670000
0#
#35711000
b10000 &
1#
#35752000
0#
#35793000
b10001 &
1#
#35834000
0#
#35875000
b10010 &
1#
#35916000
0#
#35957000
b10011 &
1#
#35998000
0#
#36039000
b10100 &
1#
#36080000
0#
#36121000
b10101 &
1#
#36162000
0#
#36203000
b10110 &
1#
#36244000
0#
#36285000
b10111 &
1#
#36326000
0#
#36367000
b11000 &
1#
#36408000
0#
#36449000
b11001 &
1#
#36490000
0#
#36531000
b11010 &
1#
#36572000
0#
#36613000
b11011 &
1#
#36654000
0#
#36695000
b11100 &
1#
#36736000
0#
#36777000
b11101 &
1#
#36818000
0#
#36859000
b11110 &
1#
#36900000
0#
#36941000
b11111 &
1#
#36982000
0#
#37023000
b100000 &
1#
#37064000
0#
#37105000
b100001 &
1#
#37146000
0#
#37187000
b100010 &
1#
#37228000
0#
#37269000
b100011 &
1#
#37310000
0#
#37351000
b100100 &
1#
#37392000
0#
#37433000
b100101 &
1#
#37474000
0#
1"
b110 $
#37515000
b100110 &
1#
#37550000
0"
#37556000
0#
#37597000
b100111 &
1#
#37638000
0#
#37676000
1"
b101 $
#37679000
b101000 &
1#
#37720000
0#
#37744000
0"
#37761000
b101001 &
1#
#37796000
1"
b100 $
#37802000
0#
#37843000
b101010 &
1#
#37884000
0#
#37909000
0"
#37925000
b101011 &
1#
#37966000
0#
#38007000
b101100 &
1#
#38037000
1"
b11 $
#38048000
0#
#38089000
b101101 &
1#
#38119000
0"
#38130000
0#
#38171000
b101110 &
1#
#38205000
1"
b10 $
#38212000
0#
#38253000
b101111 &
1#
#38286000
0"
#38294000
0#
#38335000
b110000 &
1#
#38376000
0#
#38391000
1"
b1 $
#38417000
b110001 &
1#
#38458000
0#
#38470000
0"
#38499000
b110010 &
1#
#38527000
1"
b0 $
#38540000
0#
#38581000
b110011 &
1#
#38622000
0#
#38663000
b110100 &
1#
#38704000
0#
#38745000
b110101 &
1#
#38786000
0#
#38827000
b110110 &
1#
#38868000
0#
#38909000
b110111 &
1#
#38950000
0#
#38991000
b111000 &
1#
#39032000
0#
#39073000
b111001 &
1#
#39114000
0#
#39155000
b111010 &
1#
#39196000
0#
#39237000
b111011 &
1#
#39278000
0#
#39319000
0'
b0 &
1#
#39360000
0#
#39401000
b1 &
1#
#39442000
0#
#39483000
b10 &
1#
#39524000
0#
#39565000
b11 &
1#
#39606000
0#
#39647000
b100 &
1#
#39688000
0#
#39729000
b101 &
1#
#39770000
0#
#39811000
b110 &
1#
#39852000
0#
#39893000
b111 &
1#
#39934000
0#
#39975000
b1000 &
1#
#40016000
0#
#40057000
b1001 &
1#
#40098000
0#
#40139000
b1010 &
1#
#40180000
0#
#40221000
b1011 &
1#
#40262000
0#
#40303000
b1100 &
1#
#40344000
0#
#40385000
b1101 &
1#
#40426000
0#
#40467000
b1110 &
1#
#40508000
0#
#40549000
b1111 &
1#
#40590000
0#
#40631000
b10000 &
1#
#40672000
0#
#40713000
b10001 &
1#
#40754000
0#
#40795000
b10010 &
1#
#40836000
0#
#40877000
b10011 &
1#
#40918000
0#
#40959000
b10100 &
1#
#41000000
0#
#41041000
b10101 &
1#
#41082000
0#
#41123000
b10110 &
1#
#41164000
0#
#41205000
b10111 &
1#
#41246000
0#
#41287000
b11000 &
1#
#41328000
0#
#41369000
b11001 &
1#
#41410000
0#
#41451000
b11010 &
1#
#41492000
0#
#41533000
b11011 &
1#
#41574000
0#
#41615000
b11100 &
1#
#41656000
0#
#41697000
b11101 &
1#
#41738000
0#
#41779000
b11110 &
1#
#41820000
0#
#41861000
b11111 &
1#
#41902000
0#
#41943000
b100000 &
1#
#41984000
0#
#42025000
b100001 &
1#
#42066000
0#
#42107000
b100010 &
1#
#42148000
0#
#42189000
b100011 &
1#
#42230000
0#
#42271000
b100100 &
1#
#42312000
0#
#42353000
b100101 &
1#
#42394000
0#
#42435000
b100110 &
1#
#42476000
0#
#42517000
b100111 &
1#
#42558000
0#
#42599000
b101000 &
1#
#42640000
0#
#42681000
b101001 &
1#
#42722000
0#
#42763000
b101010 &
1#
#42804000
0#
#42845000
b101011 &
1#
#42886000
0#
#42927000
b101100 &
1#
#42968000
0#
#43009000
b101101 &
1#
#43050000
0#
#43091000
b101110 &
1#
#43132000
0#
#43173000
b101111 &
1#
#43214000
0#
#43255000
b110000 &
1#
#43296000
0#
#43337000
b110001 &
1#
#43378000
0#
#43419000
b110010 &
1#
#43460000
0#
#43501000
b110011 &
1#
#43542000
0#
#43583000
b110100 &
1#
#43624000
0#
#43665000
b110101 &
1#
#43706000
0#
#43747000
b110110 &
1#
#43788000
0#
#43829000
b110111 &
1#
#43870000
0#
#43911000
b111000 &
1#
#43952000
0#
#43993000
b111001 &
1#
#44034000
0#
#44075000
b111010 &
1#
#44116000
0#
#44157000
b111011 &
1#
#44198000
0#
#44239000
1!
1(
1'
b0 &
1#
#44280000
0#
#44321000
b1 &
1#
#44362000
0#
#44403000
b10 &
1#
#44444000
0#
#44485000
b11 &
1#
#44526000
0#
#44567000
b100 &
1#
#44608000
0#
#44649000
b101 &
1#
#44690000
0#
#44731000
b110 &
1#
#44772000
0#
#44813000
b111 &
1#
#44854000
0#
#44895000
b1000 &
1#
#44936000
0#
#44977000
b1001 &
1#
#45018000
0#
#45059000
b1010 &
1#
#45100000
0#
#45110000
0"
#45141000
b1011 &
1#
#45182000
0#
#45223000
b1100 &
1#
#45264000
0#
#45305000
b1101 &
1#
#45346000
0#
#45387000
b1110 &
1#
#45428000
0#
#45469000
b1111 &
1#
#45510000
0#
#45551000
b10000 &
1#
#45592000
0#
#45633000
b10001 &
1#
#45674000
0#
#45715000
b10010 &
1#
#45756000
0#
#45797000
b10011 &
1#
#45838000
0#
#45879000
b10100 &
1#
#45920000
0#
#45961000
b10101 &
1#
#46002000
0#
#46043000
b10110 &
1#
#46084000
0#
#46125000
b10111 &
1#
#46166000
0#
#46207000
b11000 &
1#
#46248000
0#
#46289000
b11001 &
1#
#46330000
0#
#46371000
b11010 &
1#
#46412000
0#
#46453000
b11011 &
1#
#46494000
0#
#46535000
b11100 &
1#
#46576000
0#
#46617000
b11101 &
1#
#46658000
0#
#46699000
b11110 &
1#
#46740000
0#
#46781000
b11111 &
1#
#46822000
0#
#46863000
b100000 &
1#
#46904000
0#
#46945000
b100001 &
1#
#46986000
0#
#47027000
b100010 &
1#
#47068000
0#
#47109000
b100011 &
1#
#47150000
0#
#47191000
b100100 &
1#
#47232000
0#
#47273000
b100101 &
1#
#47314000
0#
#47355000
b100110 &
1#
#47396000
0#
#47437000
b100111 &
1#
#47478000
0#
#47519000
b101000 &
1#
#47560000
0#
#47601000
b101001 &
1#
#47642000
0#
#47683000
b101010 &
1#
#47724000
0#
#47765000
b101011 &
1#
#47806000
0#
#47847000
b101100 &
1#
#47888000
0#
#47929000
b101101 &
1#
#47970000
0#
#48011000
b101110 &
1#
#48052000
0#
#48093000
b101111 &
1#
#48134000
0#
#48175000
b110000 &
1#
#48216000
0#
#48257000
b110001 &
1#
#48298000
0#
#48339000
b110010 &
1#
#48380000
0#
#48421000
b110011 &
1#
#48462000
0#
#48503000
b110100 &
1#
#48544000
0#
#48585000
b110101 &
1#
#48626000
0#
#48667000
b110110 &
1#
#48708000
0#
#48749000
b110111 &
1#
#48790000
0#
#48831000
b111000 &
1#
#48872000
0#
#48913000
b111001 &
1#
